qpz_atomics/__init__.py
qpz_atomics/qpz_atomics.py
qpz_atomics/skeleton.py
qpz_atomics/atomics/__init__.py
qpz_atomics/atomics/gate.py
qpz_atomics/atomics/meas.py
qpz_atomics/atomics/prep.py
qpz_atomics/atomics/pres.py
qpz_atomics/atomics/test.py
qpz_atomics/atomics/util.py
qpz_atomics/mappings/__init__.py
qpz_atomics/mappings/qunetsim.py
qpz_atomics/mappings/simulaqron.py
qpz_atomics-1.0.0.dist-info/AUTHORS.rst
qpz_atomics-1.0.0.dist-info/LICENSE.txt
qpz_atomics-1.0.0.dist-info/METADATA
qpz_atomics-1.0.0.dist-info/WHEEL
qpz_atomics-1.0.0.dist-info/top_level.txt
qpz_atomics-1.0.0.dist-info/RECORD
