Metadata-Version: 2.1
Name: qpz-atomics
Version: 1.0.0
Summary: Quantum Protocol Zoo Atomic Functions Library
Home-page: https://github.com/quantumprotocolzoo/qpz_atomics
Author: Harold Ollivier
Author-email: harold.ollivier@mines.org
License: mit
Project-URL: Documentation, https://github.com/quantumprotocolzoo/qpz_atomics/docs
Platform: any
Classifier: Development Status :: 4 - Beta
Classifier: Programming Language :: Python
Requires-Python: >=3.6
Requires-Dist: simulaqron
Requires-Dist: cqc
Requires-Dist: hypothesis
Provides-Extra: testing
Requires-Dist: pytest ; extra == 'testing'
Requires-Dist: pytest-cov ; extra == 'testing'
